ncert_dl/__init__.py
ncert_dl/cli.py
ncert_dl/syllabus.json
ncert_dl-1.0.2.dist-info/licenses/LICENSE
ncert_dl-1.0.2.dist-info/METADATA
ncert_dl-1.0.2.dist-info/WHEEL
ncert_dl-1.0.2.dist-info/entry_points.txt
ncert_dl-1.0.2.dist-info/top_level.txt
ncert_dl-1.0.2.dist-info/RECORD
