Metadata-Version: 2.4
Name: ncert-dl
Version: 1.0.2
Summary: NCERT textbook downloader for Classes 6–12
Author: Parth Dalal
License-Expression: MIT
Classifier: Programming Language :: Python :: 3
Classifier: Operating System :: OS Independent
Requires-Python: >=3.9
License-File: LICENSE
Requires-Dist: requests
Requires-Dist: tqdm
Requires-Dist: questionary
Requires-Dist: rich
Dynamic: license-file
